rsync_watch/__init__.py
rsync_watch/check.py
rsync_watch/cli.py
rsync_watch-0.7.2.dist-info/LICENSE
rsync_watch-0.7.2.dist-info/METADATA
rsync_watch-0.7.2.dist-info/WHEEL
rsync_watch-0.7.2.dist-info/entry_points.txt
rsync_watch-0.7.2.dist-info/RECORD
