Metadata-Version: 2.1
Name: rsync_watch
Version: 0.7.2
Summary: A Python script to monitor the execution of a rsync task.
Home-page: https://github.com/Josef-Friedrich/rsync-watch
License: GPL-3.0-only
Author: Josef Friedrich
Author-email: josef@friedrich.rocks
Requires-Python: >=3.10,<4.0
Classifier: Development Status :: 5 - Production/Stable
Classifier: License :: OSI Approved :: GNU General Public License v3 (GPLv3)
Classifier: Programming Language :: Python :: 3
Classifier: Programming Language :: Python :: 3.10
Classifier: Programming Language :: Python :: 3.11
Classifier: Programming Language :: Python :: 3.12
Requires-Dist: command-watcher (>=0.4.1,<0.5.0)
Requires-Dist: conf2levels (>=0,<1)
Project-URL: Repository, https://github.com/Josef-Friedrich/rsync-watch
